lambada/__init__.py
lambada/cli.py
lambada/common.py
lambada/tests/__init__.py
lambada/tests/common.py
lambada/tests/test_cli.py
lambada/tests/test_common.py
lambada/tests/test_lambada.py
lambada/tests/test_package.py
lambada-0.2.1.dist-info/DESCRIPTION.rst
lambada-0.2.1.dist-info/entry_points.txt
lambada-0.2.1.dist-info/METADATA
lambada-0.2.1.dist-info/metadata.json
lambada-0.2.1.dist-info/RECORD
lambada-0.2.1.dist-info/top_level.txt
lambada-0.2.1.dist-info/WHEEL
lambada-0.2.1.dist-info/zip-safe
