Metadata-Version: 2.0
Name: lambada
Version: 0.2.1
Summary: A framework for multiple AWS lambdas in one library/package
Home-page: https://github.com/Superpedestrian/lambada
Author: Superpedestrian, Inc
Author-email: dev@superpedetrian.com
License: License :: OSI Approved :: Apache Software License
Platform: UNKNOWN
Classifier: Development Status :: 2 - Pre-Alpha
Requires-Dist: lambda-uploader
Requires-Dist: click
Requires-Dist: PyYAML
Requires-Dist: six
